{"coherence": -0.13844994761113047, "top_tokens": [["posrednici", "petooktobarskih", "spre\u010davanje", "blok", "vesli", "eskalacija", "pri\u0161ao", "jednaka", "komunisti\u010dki", "pregovara\u010di"], ["srbije", "ipak", "nam", "bez", "zato", "stranke", "problem", "pitanje", "ima", "srbija"], ["\u0161ta", "biv\u0161i", "evropska", "bude", "ako", "evropskom", "ponovo", "toga", "tome", "evropskoj"], ["rekao", "sastanak", "rusija", "trampa", "rusije", "donalda", "tramp", "severnoj", "ameri\u010dki", "ameri\u010dkim"], ["srbije", "\u0161ta", "bilo", "ve\u0107", "ka\u017ee", "jer", "smo", "bbc", "bio", "pitanje"], ["godinu", "deca", "koliko", "imali", "ka\u017ee", "istra\u017eivanje", "decu", "svega", "tada", "\u010dak"], ["zna\u010di", "druge", "nego", "budu", "kompanije", "na\u010din", "beogradu", "nove", "mogu", "svega"], ["ministar", "tramp", "odsto", "sad", "predsednik", "sporazum", "zakon", "vlade", "tri", "nakon"], ["irana", "siriji", "dozvolu", "tu\u017eilac", "pro\u0161le", "trupe", "pokrenuo", "zvani\u010dnici", "voz", "tvrde"], ["ameri\u010dki", "najmanje", "donald", "gradu", "sad", "zvani\u010dnika", "ju\u017enoj", "epa", "afp", "tramp"], ["srbije", "nema", "iako", "jer", "beogradu", "bez", "ka\u017ee", "srbiji", "sve", "pri\u010da"], ["prvaka", "nadam", "titula", "huan", "njihovoj", "vatrogasci", "pro\u010ditao", "200", "doktorka", "postignete"], ["dugo", "preko", "deset", "ljudi", "koga", "odnosno", "najavio", "onda", "dobio", "radio"], ["kad", "tome", "ona", "sve", "taj", "zato", "tim", "jedan", "ili", "ako"], ["blok", "petooktobarskih", "kuvara", "domenu", "stop", "komunisti\u010dki", "konsultant", "sume", "ciljem", "titula"], ["uklju\u010duju\u0107i", "fejsbuk", "ruskog", "svetsko", "dru\u0161tvenim", "ruska", "pokrenuo", "ministarka", "vest", "mre\u017eama"], ["istragu", "novinari", "pru\u017ei", "prvaka", "ubijeno", "670", "\u0107erka", "porodice", "popularnost", "poginulo"], ["neprijatnost", "malu", "selu", "670", "utvrdila", "umetnik", "data", "dr\u017eavi", "licu", "krvavim"], ["tvrdi", "dr\u017eave", "ameri\u010dke", "sud", "predsednik", "predsednika", "ova", "nakon", "trampa", "tramp"], ["srbija", "ministar", "prava", "nisu", "srbije", "evropska", "pravo", "za\u0161to", "evropske", "zakon"]], "diversity": 0.83, "dataset": "news", "embedding_method": "CTM", "model": "CTM", "topic_method": "CTM", "language": "indonesian", "dataset_length": 1625, "average_document_length": 206.0, "vocab_size": 33548, "training_time": 54.30531024932861}