{"coherence": 0.004395349368195524, "teacher_coherence": 0.1375768085615637, "top_tokens": [["rekao", "policija", "zbog", "nakon", "rekla", "protiv", "afp", "tvrdi", "reuters", "pro\u0161le"], ["rekao", "predsednik", "sad", "nakon", "predsednika", "protiv", "ne\u0107e", "biti", "izme\u0111u", "na\u010din"], ["sad", "predsednik", "rekao", "tokom", "zbog", "izjavio", "izme\u0111u", "\u017eeli", "biti", "nakon"], ["sam", "srbije", "bila", "ka\u017ee", "srbiji", "nisu", "prvi", "smo", "bilo", "ako"], ["ni\u0161ta", "njegova", "mesta", "000", "drugi", "druge", "protiv", "vlasti", "prava", "meseca"], ["predsednik", "sad", "rekao", "izjavio", "dr\u017eave", "predsednika", "izme\u0111u", "ne\u0107e", "nakon", "biti"], ["\u010detiri", "meseca", "mestu", "toga", "kome", "poput", "mnogo", "tri", "gotovo", "kad"], ["srbije", "srbiji", "mo\u017ee", "bilo", "samo", "neke", "\u0161ta", "jo\u0161", "ka\u017ee", "prema"], ["predsednik", "rekao", "afp", "sad", "zbog", "nakon", "policija", "tokom", "izjavio", "ove"], ["sam", "ka\u017ee", "bio", "smo", "jedan", "nekoliko", "zbog", "bila", "godina", "kad"], ["jo\u0161", "dana", "smo", "bilo", "bila", "nisu", "nakon", "nekoliko", "gde", "bio"], ["neke", "drugi", "druge", "ni\u0161ta", "000", "ponovo", "mesta", "nove", "mestu", "2017"], ["sam", "ka\u017ee", "bila", "kad", "ili", "smo", "bio", "jo\u0161", "joj", "bilo"], ["bio", "sam", "smo", "ka\u017ee", "godina", "svi", "ili", "bila", "prvi", "zbog"], ["odsto", "manje", "ili", "mogu", "ljudi", "mo\u017ee", "getty", "images", "koliko", "ako"], ["ka\u017ee", "mo\u017ee", "ili", "ljudi", "vreme", "sve", "srbiji", "sam", "mogu", "prema"], ["ka\u017ee", "tri", "nego", "ima", "svoju", "posle", "kad", "vi\u0161e", "jedna", "mogao"], ["predsednik", "rekao", "sad", "nakon", "predsednika", "izme\u0111u", "tako\u0111e", "izjavio", "zbog", "reuters"], ["srbije", "srbiji", "ako", "bez", "images", "prema", "getty", "biti", "ka\u017ee", "jer"], ["pre", "sam", "jo\u0161", "bila", "samo", "imao", "ka\u017ee", "bilo", "prvi", "dok"]], "teacher_top_tokens": [["court", "judge", "prison", "trial", "guilty", "police", "charges", "prosecutors", "justice", "jury"], ["party", "clinton", "trump", "labour", "election", "voters", "republican", "bush", "would", "vote"], ["like", "get", "even", "time", "people", "much", "really", "think", "never", "many"], ["game", "players", "league", "season", "team", "games", "cup", "coach", "ball", "play"], ["labour", "tax", "party", "government", "cameron", "minister", "scottish", "mps", "abbott", "prime"], ["clinton", "obama", "trump", "republican", "bush", "state", "president", "republicans", "hillary", "presidential"], ["tea", "sweden", "grade", "howard", "miller", "kong", "wood", "jean", "bear", "evans"], ["per", "market", "oil", "cent", "prices", "sales", "growth", "bank", "investors", "price"], ["isis", "islamic", "syrian", "migrants", "syria", "refugees", "military", "forces", "attacks", "killed"], ["game", "players", "cup", "coach", "games", "league", "season", "team", "ball", "win"], ["police", "fire", "officers", "crash", "car", "shooting", "killed", "man", "officer", "plane"], ["health", "school", "schools", "patients", "nhs", "students", "cancer", "children", "care", "education"], ["family", "mother", "mrs", "told", "daughter", "children", "baby", "son", "woman", "died"], ["film", "photo", "music", "actress", "movie", "star", "los", "actor", "fashion", "awards"], ["researchers", "scientists", "cancer", "brain", "study", "cells", "patients", "research", "disease", "may"], ["water", "weather", "snow", "city", "rain", "space", "storm", "homes", "temperatures", "river"], ["tea", "sweden", "howard", "ford", "grade", "miller", "kong", "evans", "maryland", "windows"], ["nuclear", "iran", "russian", "russia", "china", "military", "putin", "korea", "chinese", "sanctions"], ["per", "market", "cent", "oil", "prices", "sales", "bank", "price", "growth", "investors"], ["game", "players", "coach", "season", "team", "win", "ball", "league", "cup", "games"]], "diversity": 0.45, "teacher_diversity": 0.76, "cls": 0.031067615374922752, "cross_lingual_toptoken_similarity": 0.42551966309547423, "dataset": "news", "embedding_method": "Pre-trained embeddings", "model": "GMM", "topic_method": "tf", "language": "indonesian", "dataset_length": 163, "average_document_length": 54.0, "vocab_size": 3865, "embedding_model": "BERT", "training_time": 6244.201409578323}